json_fnl/__init__.py
json_fnl/__main__.py
JsonFNL-0.1.5.dist-info/LICENSE.txt
JsonFNL-0.1.5.dist-info/METADATA
JsonFNL-0.1.5.dist-info/WHEEL
JsonFNL-0.1.5.dist-info/top_level.txt
JsonFNL-0.1.5.dist-info/RECORD
