Metadata-Version: 2.1
Name: JsonFNL
Version: 0.1.5
Summary: Find and lint all json files
Home-page: https://github.com/dgs3/json_fnl
Author: Dave Sayles
Author-email: sayles.dave@gmail.com
License: "BSD"
Platform: UNKNOWN
Classifier: Programming Language :: Python :: 3
Classifier: License :: OSI Approved :: BSD License
Classifier: Operating System :: OS Independent
Classifier: Programming Language :: Python
Classifier: Programming Language :: Python :: 3
Classifier: Topic :: Software Development :: Libraries :: Python Modules
Requires-Python: >=3.3
License-File: LICENSE.txt
